gxf/__init__.py
gxf/field.py
gxf/gxf.py
gxf/operator.py
gxf/util.py
gxf-0.0.5.dist-info/METADATA
gxf-0.0.5.dist-info/WHEEL
gxf-0.0.5.dist-info/top_level.txt
gxf-0.0.5.dist-info/RECORD
